<?xml version="1.0" encoding="utf-8" ?>
<dwsync>
<file name="2-22-0.gif" server="www.nteach4u.com/Webpage/htdocs/" local="129023171840000000" remote="129949479600000000" />
<file name="2-25-0.gif" server="www.nteach4u.com/Webpage/htdocs/" local="129023171840000000" remote="129949479600000000" />
<file name="2-26-0.gif" server="www.nteach4u.com/Webpage/htdocs/" local="129023171840000000" remote="129949479600000000" />
<file name="2-27-1.gif" server="www.nteach4u.com/Webpage/htdocs/" local="129023171840000000" remote="129949479600000000" />
<file name="2-27-2.gif" server="www.nteach4u.com/Webpage/htdocs/" local="129023171840000000" remote="129949479600000000" />
<file name="2-27-3.gif" server="www.nteach4u.com/Webpage/htdocs/" local="129023171840000000" remote="129949479600000000" />
<file name="2-27-4.gif" server="www.nteach4u.com/Webpage/htdocs/" local="129023171840000000" remote="129949479600000000" />
<file name="2-28-0.gif" server="www.nteach4u.com/Webpage/htdocs/" local="129023171860000000" remote="129949479600000000" />
<file name="2-30-0.gif" server="www.nteach4u.com/Webpage/htdocs/" local="129023171860000000" remote="129949479600000000" />
<file name="2-33-0.gif" server="www.nteach4u.com/Webpage/htdocs/" local="129023171860000000" remote="129949479600000000" />
<file name="2-36-0.gif" server="www.nteach4u.com/Webpage/htdocs/" local="129023171860000000" remote="129949479600000000" />
<file name="2-38-0.gif" server="www.nteach4u.com/Webpage/htdocs/" local="129023171860000000" remote="129949479600000000" />
<file name="2-39-0.gif" server="www.nteach4u.com/Webpage/htdocs/" local="129023171860000000" remote="129949479600000000" />
<file name="3-49-0.gif" server="www.nteach4u.com/Webpage/htdocs/" local="129023171860000000" remote="129949479600000000" />
<file name="3-54-0.gif" server="www.nteach4u.com/Webpage/htdocs/" local="129023171860000000" remote="129949479600000000" />
<file name="3-58-0.gif" server="www.nteach4u.com/Webpage/htdocs/" local="129023171860000000" remote="129949479600000000" />
<file name="C127-25-view-1.gif" server="www.nteach4u.com/Webpage/htdocs/" local="129023171860000000" remote="129949479600000000" />
<file name="C127-26-view-1.gif" server="www.nteach4u.com/Webpage/htdocs/" local="129023171860000000" remote="129949479600000000" />
</dwsync>